semantik/__init__.py
semantik/client.py
semantik/py.typed
semantik/http/__init__.py
semantik/http/base_client.py
semantik/resources/__init__.py
semantik/resources/candidates.py
semantik/resources/programs.py
semantik_sdk-0.1.3.dist-info/METADATA
semantik_sdk-0.1.3.dist-info/WHEEL
semantik_sdk-0.1.3.dist-info/top_level.txt
semantik_sdk-0.1.3.dist-info/RECORD
