Metadata-Version: 2.4
Name: semantik-sdk
Version: 0.1.3
Summary: Python SDK for the Semantik Client API
Author-email: Semantik <support@semantikmatch.com>
License: MIT
Project-URL: Homepage, https://github.com/your-org/semantik
Project-URL: Documentation, https://docs.semantikmatch.com
Project-URL: Repository, https://github.com/your-org/semantik
Keywords: semantik,sdk,api,students
Classifier: Development Status :: 4 - Beta
Classifier: Intended Audience :: Developers
Classifier: License :: OSI Approved :: MIT License
Classifier: Programming Language :: Python :: 3
Classifier: Programming Language :: Python :: 3.8
Classifier: Programming Language :: Python :: 3.9
Classifier: Programming Language :: Python :: 3.10
Classifier: Programming Language :: Python :: 3.11
Classifier: Programming Language :: Python :: 3.12
Requires-Python: >=3.8
Requires-Dist: requests>=2.31.0
Provides-Extra: dev
Requires-Dist: pytest>=7.4.0; extra == "dev"
Requires-Dist: pytest-asyncio>=0.21.0; extra == "dev"
Requires-Dist: black>=23.0.0; extra == "dev"
Requires-Dist: mypy>=1.5.0; extra == "dev"
Requires-Dist: ruff>=0.1.0; extra == "dev"
Dynamic: requires-python
